rmnpy-0.2.0.dist-info/RECORD
rmnpy-0.2.0.dist-info/WHEEL
rmnpy-0.2.0.dist-info/top_level.txt
rmnpy-0.2.0.dist-info/METADATA
rmnpy/quantities.pyx
rmnpy/quantities.cpython-311-darwin.so
rmnpy/__init__.py
rmnpy/quantities.pyi
rmnpy/exceptions.py
rmnpy/dll_loader.py
rmnpy/math.py
rmnpy/quantities.c
rmnpy/wrappers/__init__.py
rmnpy/wrappers/rmnlib/dependent_variable.cpython-311-darwin.so
rmnpy/wrappers/rmnlib/dependent_variable.c
rmnpy/wrappers/rmnlib/dimension.pyx
rmnpy/wrappers/rmnlib/__init__.py
rmnpy/wrappers/rmnlib/dimension.c
rmnpy/wrappers/rmnlib/sparse_sampling.pyx
rmnpy/wrappers/rmnlib/sparse_sampling.c
rmnpy/wrappers/rmnlib/dependent_variable.pyx
rmnpy/wrappers/rmnlib/dependent_variable.pxd
rmnpy/wrappers/rmnlib/sparse_sampling.cpython-311-darwin.so
rmnpy/wrappers/rmnlib/sparse_sampling.pxd
rmnpy/wrappers/rmnlib/dimension.cpython-311-darwin.so
rmnpy/wrappers/rmnlib/dimension.pxd
rmnpy/wrappers/sitypes/dimensionality.pyx
rmnpy/wrappers/sitypes/unit.cpython-311-darwin.so
rmnpy/wrappers/sitypes/dimensionality.c
rmnpy/wrappers/sitypes/scalar.pxd
rmnpy/wrappers/sitypes/unit.pyx
rmnpy/wrappers/sitypes/__init__.py
rmnpy/wrappers/sitypes/dimensionality.cpython-311-darwin.so
rmnpy/wrappers/sitypes/scalar.pyx
rmnpy/wrappers/sitypes/unit.pxd
rmnpy/wrappers/sitypes/scalar.cpython-311-darwin.so
rmnpy/wrappers/sitypes/scalar.c
rmnpy/wrappers/sitypes/dimensionality.pxd
rmnpy/wrappers/sitypes/unit.c
rmnpy/rmnlib/__init__.py
rmnpy/sitypes/__init__.py
rmnpy/.dylibs/libSITypes.dylib
rmnpy/.dylibs/libOCTypes.dylib
rmnpy/.dylibs/libRMN.dylib
rmnpy/_c_api/octypes.pxd
rmnpy/_c_api/__init__.py
rmnpy/_c_api/sitypes.pxd
rmnpy/_c_api/rmnlib.pxd
rmnpy/helpers/octypes.c
rmnpy/helpers/__init__.py
rmnpy/helpers/octypes.cpython-311-darwin.so
rmnpy/helpers/octypes.pyx
