Metadata-Version: 2.4
Name: rmnpy
Version: 0.2.0
Summary: Python bindings for OCTypes, SITypes, and RMNLib C libraries for scientific computing with units and dimensional analysis
Author-email: Philip Grandinetti <grandinetti.1@osu.edu>
Maintainer-email: Philip Grandinetti <grandinetti.1@osu.edu>
License: MIT
Project-URL: Homepage, https://github.com/pjgrandinetti/RMNpy
Project-URL: Documentation, https://rmnpy.readthedocs.io
Project-URL: Repository, https://github.com/pjgrandinetti/RMNpy
Project-URL: Source Code, https://github.com/pjgrandinetti/RMNpy
Project-URL: Bug Reports, https://github.com/pjgrandinetti/RMNpy/issues
Project-URL: Changelog, https://github.com/pjgrandinetti/RMNpy/blob/master/CHANGELOG.md
Project-URL: CI/CD, https://github.com/pjgrandinetti/RMNpy/actions
Keywords: scientific-computing,units,dimensional-analysis,nmr,spectroscopy,physics,chemistry,c-extensions,cython
Classifier: Development Status :: 3 - Alpha
Classifier: Intended Audience :: Science/Research
Classifier: License :: OSI Approved :: MIT License
Classifier: Operating System :: POSIX :: Linux
Classifier: Operating System :: MacOS
Classifier: Operating System :: Microsoft :: Windows
Classifier: Programming Language :: Python :: 3
Classifier: Programming Language :: Python :: 3.11
Classifier: Programming Language :: Python :: 3.12
Classifier: Programming Language :: Python :: 3 :: Only
Classifier: Programming Language :: C
Classifier: Programming Language :: Cython
Classifier: Topic :: Scientific/Engineering
Classifier: Topic :: Software Development :: Libraries :: Python Modules
Classifier: Typing :: Typed
Requires-Python: >=3.11
Requires-Dist: numpy>=1.23; python_version == "3.11"
Requires-Dist: numpy>=1.26; python_version >= "3.12"
Provides-Extra: dev
Requires-Dist: pytest>=6.2.0; extra == "dev"
Requires-Dist: pytest-cov>=2.12.0; extra == "dev"
Requires-Dist: pytest-xdist>=2.4.0; extra == "dev"
Requires-Dist: black>=21.0.0; extra == "dev"
Requires-Dist: isort>=5.9.0; extra == "dev"
Requires-Dist: flake8>=3.9.0; extra == "dev"
Requires-Dist: mypy>=0.910; extra == "dev"
Requires-Dist: pre-commit>=2.15.0; extra == "dev"
Provides-Extra: docs
Requires-Dist: sphinx>=3.1.0; extra == "docs"
Requires-Dist: sphinx-rtd-theme>=0.5.2; extra == "docs"
Requires-Dist: breathe>=4.13.0; extra == "docs"
Requires-Dist: myst-parser>=0.15.0; extra == "docs"
Requires-Dist: sphinx-copybutton>=0.3.0; extra == "docs"
Provides-Extra: test
Requires-Dist: pytest>=6.2.0; extra == "test"
Requires-Dist: pytest-cov>=2.12.0; extra == "test"
Requires-Dist: pytest-xdist>=2.4.0; extra == "test"
Requires-Dist: pytest-benchmark>=3.4.0; extra == "test"
Provides-Extra: all
Requires-Dist: rmnpy[dev,docs,test]; extra == "all"
